pdchaos/middleware/contrib/django/__init__.py
pdchaos/middleware/contrib/django/django_config.py
pdchaos/middleware/contrib/django/django_middleware.py
pdchaos/middleware/contrib/django/version.py
proofdock_chaos_middleware_django-0.1.0.dist-info/METADATA
proofdock_chaos_middleware_django-0.1.0.dist-info/WHEEL
proofdock_chaos_middleware_django-0.1.0.dist-info/top_level.txt
proofdock_chaos_middleware_django-0.1.0.dist-info/RECORD
